Classfile /E:/__PROJECT__/JAVA/BookShildt_003/out/production/BookShildt_003/e0101_Meta_Wildcard_2_from_youtube/Point.class
  Last modified 10 ����. 2023 �.; size 1265 bytes
  SHA-256 checksum 1be91bb469905dce8d5c540fc39c2178961ee03e3bad36b2b3c7047d38e80f4d
  Compiled from "Point.java"
public class e0101_Meta_Wildcard_2_from_youtube.Point<T extends java.lang.Number> extends java.lang.Object
  minor version: 0
  major version: 61
  flags: (0x0021) ACC_PUBLIC, ACC_SUPER
  this_class: #8                          // e0101_Meta_Wildcard_2_from_youtube/Point
  super_class: #2                         // java/lang/Object
  interfaces: 0, fields: 2, methods: 3, attributes: 2
Constant pool:
   #1 = Methodref          #2.#3          // java/lang/Object."<init>":()V
   #2 = Class              #4             // java/lang/Object
   #3 = NameAndType        #5:#6          // "<init>":()V
   #4 = Utf8               java/lang/Object
   #5 = Utf8               <init>
   #6 = Utf8               ()V
   #7 = Fieldref           #8.#9          // e0101_Meta_Wildcard_2_from_youtube/Point.x:Ljava/lang/Number;
   #8 = Class              #10            // e0101_Meta_Wildcard_2_from_youtube/Point
   #9 = NameAndType        #11:#12        // x:Ljava/lang/Number;
  #10 = Utf8               e0101_Meta_Wildcard_2_from_youtube/Point
  #11 = Utf8               x
  #12 = Utf8               Ljava/lang/Number;
  #13 = Fieldref           #8.#14         // e0101_Meta_Wildcard_2_from_youtube/Point.y:Ljava/lang/Number;
  #14 = NameAndType        #15:#12        // y:Ljava/lang/Number;
  #15 = Utf8               y
  #16 = Methodref          #17.#18        // java/lang/Number.doubleValue:()D
  #17 = Class              #19            // java/lang/Number
  #18 = NameAndType        #20:#21        // doubleValue:()D
  #19 = Utf8               java/lang/Number
  #20 = Utf8               doubleValue
  #21 = Utf8               ()D
  #22 = Methodref          #23.#24        // java/lang/Math.max:(DD)D
  #23 = Class              #25            // java/lang/Math
  #24 = NameAndType        #26:#27        // max:(DD)D
  #25 = Utf8               java/lang/Math
  #26 = Utf8               max
  #27 = Utf8               (DD)D
  #28 = Utf8               Signature
  #29 = Utf8               TT;
  #30 = Utf8               (Ljava/lang/Number;Ljava/lang/Number;)V
  #31 = Utf8               Code
  #32 = Utf8               LineNumberTable
  #33 = Utf8               LocalVariableTable
  #34 = Utf8               this
  #35 = Utf8               Le0101_Meta_Wildcard_2_from_youtube/Point;
  #36 = Utf8               LocalVariableTypeTable
  #37 = Utf8               Le0101_Meta_Wildcard_2_from_youtube/Point<TT;>;
  #38 = Utf8               (TT;TT;)V
  #39 = Utf8               getMax
  #40 = Utf8               xd
  #41 = Utf8               D
  #42 = Utf8               yd
  #43 = Utf8               equalsPoint
  #44 = Utf8               (Le0101_Meta_Wildcard_2_from_youtube/Point;)Z
  #45 = Utf8               pt
  #46 = Utf8               Le0101_Meta_Wildcard_2_from_youtube/Point<*>;
  #47 = Utf8               StackMapTable
  #48 = Utf8               (Le0101_Meta_Wildcard_2_from_youtube/Point<*>;)Z
  #49 = Utf8               <T:Ljava/lang/Number;>Ljava/lang/Object;
  #50 = Utf8               SourceFile
  #51 = Utf8               Point.java
{
  public T x;
    descriptor: Ljava/lang/Number;
    flags: (0x0001) ACC_PUBLIC
    Signature: #29                          // TT;

  public T y;
    descriptor: Ljava/lang/Number;
    flags: (0x0001) ACC_PUBLIC
    Signature: #29                          // TT;

  e0101_Meta_Wildcard_2_from_youtube.Point(T, T);
    descriptor: (Ljava/lang/Number;Ljava/lang/Number;)V
    flags: (0x0000)
    Code:
      stack=2, locals=3, args_size=3
         0: aload_0
         1: invokespecial #1                  // Method java/lang/Object."<init>":()V
         4: aload_0
         5: aload_1
         6: putfield      #7                  // Field x:Ljava/lang/Number;
         9: aload_0
        10: aload_2
        11: putfield      #13                 // Field y:Ljava/lang/Number;
        14: return
      LineNumberTable:
        line 7: 0
        line 8: 4
        line 9: 9
        line 10: 14
      LocalVariableTable:
        Start  Length  Slot  Name   Signature
            0      15     0  this   Le0101_Meta_Wildcard_2_from_youtube/Point;
            0      15     1     x   Ljava/lang/Number;
            0      15     2     y   Ljava/lang/Number;
      LocalVariableTypeTable:
        Start  Length  Slot  Name   Signature
            0      15     0  this   Le0101_Meta_Wildcard_2_from_youtube/Point<TT;>;
            0      15     1     x   TT;
            0      15     2     y   TT;
    Signature: #38                          // (TT;TT;)V

  double getMax();
    descriptor: ()D
    flags: (0x0000)
    Code:
      stack=4, locals=5, args_size=1
         0: aload_0
         1: getfield      #7                  // Field x:Ljava/lang/Number;
         4: invokevirtual #16                 // Method java/lang/Number.doubleValue:()D
         7: dstore_1
         8: aload_0
         9: getfield      #13                 // Field y:Ljava/lang/Number;
        12: invokevirtual #16                 // Method java/lang/Number.doubleValue:()D
        15: dstore_3
        16: dload_1
        17: dload_3
        18: invokestatic  #22                 // Method java/lang/Math.max:(DD)D
        21: dreturn
      LineNumberTable:
        line 13: 0
        line 14: 8
        line 15: 16
      LocalVariableTable:
        Start  Length  Slot  Name   Signature
            0      22     0  this   Le0101_Meta_Wildcard_2_from_youtube/Point;
            8      14     1    xd   D
           16       6     3    yd   D
      LocalVariableTypeTable:
        Start  Length  Slot  Name   Signature
            0      22     0  this   Le0101_Meta_Wildcard_2_from_youtube/Point<TT;>;

  boolean equalsPoint(e0101_Meta_Wildcard_2_from_youtube.Point<?>);
    descriptor: (Le0101_Meta_Wildcard_2_from_youtube/Point;)Z
    flags: (0x0000)
    Code:
      stack=4, locals=2, args_size=2
         0: aload_0
         1: getfield      #7                  // Field x:Ljava/lang/Number;
         4: invokevirtual #16                 // Method java/lang/Number.doubleValue:()D

         7: aload_1
         8: getfield      #7                  // Field x:Ljava/lang/Number;
        11: invokevirtual #16                 // Method java/lang/Number.doubleValue:()D

        14: dcmpl
        15: ifne          40
        
        18: aload_0
        19: getfield      #13                 // Field y:Ljava/lang/Number;
        22: invokevirtual #16                 // Method java/lang/Number.doubleValue:()D
        
        25: aload_1
        26: getfield      #13                 // Field y:Ljava/lang/Number;
        29: invokevirtual #16                 // Method java/lang/Number.doubleValue:()D
        
        32: dcmpl
        33: ifne          40
        36: iconst_1
        37: goto          41
        
        40: iconst_0

        41: ireturn
      LineNumberTable:
        line 19: 0
        line 20: 22
        line 19: 41
      LocalVariableTable:
        Start  Length  Slot  Name   Signature
            0      42     0  this   Le0101_Meta_Wildcard_2_from_youtube/Point;
            0      42     1    pt   Le0101_Meta_Wildcard_2_from_youtube/Point;
      LocalVariableTypeTable:
        Start  Length  Slot  Name   Signature
            0      42     0  this   Le0101_Meta_Wildcard_2_from_youtube/Point<TT;>;
            0      42     1    pt   Le0101_Meta_Wildcard_2_from_youtube/Point<*>;
      StackMapTable: number_of_entries = 2
        frame_type = 40 /* same */ 
        frame_type = 64 /* same_locals_1_stack_item */ 
          stack = [ int ]
    Signature: #48                          // (Le0101_Meta_Wildcard_2_from_youtube/Point<*>;)Z
}
Signature: #49                          // <T:Ljava/lang/Number;>Ljava/lang/Object;
SourceFile: "Point.java"
#############################################################################################
package e0101_Meta_Wildcard_2_from_youtube;

public class Point<T extends Number> {
    public T x;
    public T y;

    Point(T x, T y) {
        this.x = x;
        this.y = y;
    }

    double getMax() {
        double xd = x.doubleValue();
        double yd = y.doubleValue();
        return Math.max(xd, yd);
    }

    boolean equalsPoint(Point<?> pt) {
        return (this.x.doubleValue() == pt.x.doubleValue() &&
                this.y.doubleValue() == pt.y.doubleValue());
    }

}
---------------------------------------------------------------------------------------------
